{
  "version": "1.1.3",
  "proposedName": "Mystery Snap",
  "description": "A simple MetaMask Snap that returns random numbers and answers.",
  "repository": {
    "type": "git",
    "url": "https://github.com/Montoya/random-snap.git"
  },
  "source": {
    "shasum": "FN9YlW8t4s188BfxLsu25BCuzMp/mbEEPlNraoNbWoE=",
    "location": {
      "npm": {
        "filePath": "dist/bundle.js",
        "iconPath": "images/icon.svg",
        "packageName": "mystery-snap",
        "registry": "https://registry.npmjs.org/"
      }
    }
  },
  "initialPermissions": {
    "snap_confirm": {}
  },
  "manifestVersion": "0.1"
}
